lavaplay/__init__.py
lavaplay/client.py
lavaplay/emitter.py
lavaplay/events.py
lavaplay/exceptions.py
lavaplay/node_manager.py
lavaplay/objects.py
lavaplay/player.py
lavaplay/rest.py
lavaplay/routes.py
lavaplay/utlits.py
lavaplay/ws.py
lavaplayer-1.0.11a0.dist-info/LICENSE
lavaplayer-1.0.11a0.dist-info/METADATA
lavaplayer-1.0.11a0.dist-info/WHEEL
lavaplayer-1.0.11a0.dist-info/top_level.txt
lavaplayer-1.0.11a0.dist-info/RECORD
